pyutils_4devs/__init__.py
pyutils_4devs/decorators/__init__.py
pyutils_4devs/decorators/cryptography.py
pyutils_4devs/decorators/file.py
pyutils_4devs/decorators/generic.py
pyutils_4devs/decorators/minio.py
pyutils_4devs/generators/__init__.py
pyutils_4devs/generators/secrets.py
pyutils_4devs/utils/__init__.py
pyutils_4devs/utils/cryptography.py
pyutils_4devs/utils/file.py
pyutils_4devs/utils/jwt.py
pyutils_4devs/utils/minio.py
pyutils_4devs-0.0.4.dist-info/LICENSE
pyutils_4devs-0.0.4.dist-info/METADATA
pyutils_4devs-0.0.4.dist-info/WHEEL
pyutils_4devs-0.0.4.dist-info/top_level.txt
pyutils_4devs-0.0.4.dist-info/RECORD
